create_joyspace.py
design.py
main.py
run_tests.py
design_mcp-0.1.4.dist-info/METADATA
design_mcp-0.1.4.dist-info/WHEEL
design_mcp-0.1.4.dist-info/entry_points.txt
design_mcp-0.1.4.dist-info/top_level.txt
design_mcp-0.1.4.dist-info/RECORD
