Metadata-Version: 2.4
Name: design-mcp
Version: 0.1.4
Summary: AI设计工具 - 实现 SSE 流式响应处理
Requires-Python: >=3.13
Requires-Dist: httpx>=0.28.1
Requires-Dist: mcp[cli]>=1.12.2
Requires-Dist: pytest>=8.4.1
Requires-Dist: pytest-asyncio>=1.1.0
